accelbyte_py_sdk/api/sessionhistory/__init__.py
accelbyte_py_sdk/api/sessionhistory/errors.py
accelbyte_py_sdk/api/sessionhistory/models/__init__.py
accelbyte_py_sdk/api/sessionhistory/models/apimodels_x_ray_bulk_ticket_observability_request.py
accelbyte_py_sdk/api/sessionhistory/models/apimodels_x_ray_bulk_ticket_observability_response.py
accelbyte_py_sdk/api/sessionhistory/models/apimodels_x_ray_ticket_observability_request.py
accelbyte_py_sdk/api/sessionhistory/models/apimodels_x_ray_ticket_observability_response.py
accelbyte_py_sdk/api/sessionhistory/models/models_alliance_rule.py
accelbyte_py_sdk/api/sessionhistory/models/models_matching_rule.py
accelbyte_py_sdk/api/sessionhistory/models/response_error.py
accelbyte_py_sdk/api/sessionhistory/operations/__init__.py
accelbyte_py_sdk/api/sessionhistory/operations/x_ray/__init__.py
accelbyte_py_sdk/api/sessionhistory/operations/x_ray/create_xray_bulk_ticket_cacbf6.py
accelbyte_py_sdk/api/sessionhistory/operations/x_ray/create_xray_ticket_obse_a825bd.py
accelbyte_py_sdk/api/sessionhistory/wrappers/__init__.py
accelbyte_py_sdk/api/sessionhistory/wrappers/_x_ray.py
accelbyte_py_sdk_service_sessionhistory-0.14.0.dist-info/METADATA
accelbyte_py_sdk_service_sessionhistory-0.14.0.dist-info/WHEEL
accelbyte_py_sdk_service_sessionhistory-0.14.0.dist-info/top_level.txt
accelbyte_py_sdk_service_sessionhistory-0.14.0.dist-info/RECORD
