Metadata-Version: 2.4
Name: accelbyte-py-sdk-service-sessionhistory
Version: 0.14.0
Summary: AccelByte Python SDK - AccelByte Gaming Services Session History Service
Requires-Python: >=3.9
Requires-Dist: accelbyte-py-sdk-core
